any_serde/__init__.py
any_serde/bytes_serde.py
any_serde/common.py
any_serde/dataclass_serde.py
any_serde/enum.py
any_serde/json_serde.py
any_serde/primitives_serde.py
any_serde/py.typed
any_serde/serde.py
any_serde/union_serde.py
any_serde/typescript/__init__.py
any_serde/typescript/bool_typedef.ts.jinja2
any_serde/typescript/dataclass_typedef.ts.jinja2
any_serde/typescript/float_typedef.ts.jinja2
any_serde/typescript/int_typedef.ts.jinja2
any_serde/typescript/list_typedef.ts.jinja2
any_serde/typescript/literal_typedef.ts.jinja2
any_serde/typescript/none_typedef.ts.jinja2
any_serde/typescript/nonetype_typedef.ts.jinja2
any_serde/typescript/string_typedef.ts.jinja2
any_serde/typescript/type_gen.py
any_serde/typescript/typescript_utils.py
any_serde/typescript/union_typedef.ts.jinja2
any_serde-0.2.18.data/data/any_serde/typescript/bool_typedef.ts.jinja2
any_serde-0.2.18.data/data/any_serde/typescript/dataclass_typedef.ts.jinja2
any_serde-0.2.18.data/data/any_serde/typescript/float_typedef.ts.jinja2
any_serde-0.2.18.data/data/any_serde/typescript/int_typedef.ts.jinja2
any_serde-0.2.18.data/data/any_serde/typescript/list_typedef.ts.jinja2
any_serde-0.2.18.data/data/any_serde/typescript/literal_typedef.ts.jinja2
any_serde-0.2.18.data/data/any_serde/typescript/none_typedef.ts.jinja2
any_serde-0.2.18.data/data/any_serde/typescript/nonetype_typedef.ts.jinja2
any_serde-0.2.18.data/data/any_serde/typescript/string_typedef.ts.jinja2
any_serde-0.2.18.data/data/any_serde/typescript/union_typedef.ts.jinja2
any_serde-0.2.18.dist-info/LICENSE
any_serde-0.2.18.dist-info/METADATA
any_serde-0.2.18.dist-info/WHEEL
any_serde-0.2.18.dist-info/top_level.txt
any_serde-0.2.18.dist-info/RECORD
