Metadata-Version: 2.1
Name: any_serde
Version: 0.2.18
License-File: LICENSE
